forge/__init__.py
forge/auth/__init__.py
forge/auth/backends.py
forge/checks.py
forge/cli.py
forge/default_settings.py
forge/email.py
forge/forms/__init__.py
forge/forms/apps.py
forge/forms/templates/django/forms/default.html
forge/forms/templates/django/forms/errors/list/default.html
forge/logging.py
forge/models.py
forge/views/__init__.py
forge/views/mixins.py
forge-0.22.0.dist-info/entry_points.txt
forge-0.22.0.dist-info/METADATA
forge-0.22.0.dist-info/LICENSE
forge-0.22.0.dist-info/WHEEL
forge-0.22.0.dist-info/RECORD
