Metadata-Version: 2.1
Name: forge
Version: 0.22.0
Summary: Quickly build a professional web app using Django.
Home-page: https://www.forgepackages.com/
License: MIT
Keywords: django,saas,forge,framework
Author: Dave Gaeddert
Author-email: dave.gaeddert@dropseed.dev
Requires-Python: >=3.8,<4.0
Classifier: Environment :: Web Environment
Classifier: Framework :: Django
Classifier: Framework :: Django :: 4
Classifier: Intended Audience :: Developers
Classifier: License :: OSI Approved :: MIT License
Classifier: Operating System :: OS Independent
Classifier: Programming Language :: Python :: 3
Classifier: Programming Language :: Python :: 3.8
Classifier: Programming Language :: Python :: 3.9
Classifier: Programming Language :: Python :: 3.10
Classifier: Programming Language :: Python :: 3.11
Requires-Dist: Django (>=4.0,<5.0)
Requires-Dist: black (>=22.12.0,<23.0.0)
Requires-Dist: click (>=8.1.0,<9.0.0)
Requires-Dist: coverage (>=7.0.1,<8.0.0)
Requires-Dist: dj-database-url (>=1.0.0,<2.0.0)
Requires-Dist: django-widget-tweaks (>=1.4.12,<2.0.0)
Requires-Dist: forge-core (<1.0.0)
Requires-Dist: forge-db (>=0.3.0,<0.4.0)
Requires-Dist: forge-heroku (<1.0.0)
Requires-Dist: forge-tailwind (<1.0.0)
Requires-Dist: forge-work (<1.0.0)
Requires-Dist: hiredis (>=2.0.0,<3.0.0)
Requires-Dist: ipython (>=8.5.0,<9.0.0)
Requires-Dist: pytest (>=7.0.0,<8.0.0)
Requires-Dist: pytest-django (>=4.5.2,<5.0.0)
Requires-Dist: python-dotenv
Requires-Dist: redis (>=4.2.2,<5.0.0)
Requires-Dist: ruff (>=0.0.194,<0.0.195)
Requires-Dist: whitenoise (>=6.0.0,<7.0.0)
Project-URL: Documentation, https://www.forgepackages.com/docs/
Project-URL: Repository, https://github.com/forgepackages/forge
